nbcell_check_cli/__init__.py
nbcell_check_cli/__main__.py
nbcell_check_cli-0.1.0.dist-info/METADATA
nbcell_check_cli-0.1.0.dist-info/WHEEL
nbcell_check_cli-0.1.0.dist-info/entry_points.txt
nbcell_check_cli-0.1.0.dist-info/RECORD
