Metadata-Version: 2.1
Name: nbcell-check-cli
Version: 0.1.0
Summary: 
Author: Ben Skubi
Author-email: bskubi@gmail.com
Requires-Python: >=3.12,<4.0
Classifier: Programming Language :: Python :: 3
Classifier: Programming Language :: Python :: 3.12
Requires-Dist: click (>=8.1.7,<9.0.0)
Requires-Dist: nbformat (>=5.9.2,<6.0.0)
